{
  "count": 222,
  "uniques": 152,
  "clones": [
    {
      "timestamp": "2021-02-03T00:00:00Z",
      "count": 5,
      "uniques": 5
    },
    {
      "timestamp": "2021-02-04T00:00:00Z",
      "count": 10,
      "uniques": 9
    },
    {
      "timestamp": "2021-02-05T00:00:00Z",
      "count": 15,
      "uniques": 13
    },
    {
      "timestamp": "2021-02-06T00:00:00Z",
      "count": 13,
      "uniques": 11
    },
    {
      "timestamp": "2021-02-07T00:00:00Z",
      "count": 19,
      "uniques": 15
    },
    {
      "timestamp": "2021-02-08T00:00:00Z",
      "count": 26,
      "uniques": 20
    },
    {
      "timestamp": "2021-02-09T00:00:00Z",
      "count": 20,
      "uniques": 16
    },
    {
      "timestamp": "2021-02-10T00:00:00Z",
      "count": 24,
      "uniques": 18
    },
    {
      "timestamp": "2021-02-11T00:00:00Z",
      "count": 19,
      "uniques": 17
    },
    {
      "timestamp": "2021-02-12T00:00:00Z",
      "count": 10,
      "uniques": 10
    },
    {
      "timestamp": "2021-02-13T00:00:00Z",
      "count": 14,
      "uniques": 13
    },
    {
      "timestamp": "2021-02-14T00:00:00Z",
      "count": 18,
      "uniques": 16
    },
    {
      "timestamp": "2021-02-15T00:00:00Z",
      "count": 14,
      "uniques": 11
    },
    {
      "timestamp": "2021-02-16T00:00:00Z",
      "count": 15,
      "uniques": 15
    }
  ]
}
